{"id": "1943", "article": "Tattoos and body piercings have moved up on the trend list in recent years . Around Western schools lots of teens are sporting new holes and \" flesh ink \" . As with all other subjects , the Chinese will surely have to deal with this situation with respect to their children . To get a better view of what has happened in the West , let ' s sit down and hear what they say . Tiara from prefix = st1 / Indiana : I personally think body piercing is sickening . If there were supposed to be holes in your body , you would have been born with them . I do , however , think that ear piercing , is not wrong . There is a difference between ear piercing and belly button piercing . Ear piercing is not nearly as dangerous . I would be sick if someone stuck a needle in my belly button . Lee fromIllinois : Hi ! I live inIllinois . I am 23 . I have 12 tattoos and three piercings . I love my tattoos and consider myself an art collector . You would be surprised at who has given me the thumbs - up on my art work . People on the street stop me to look at the tattoo on my leg . Most of them do n ' t know what it is . They just think the work itself is great . Subotai fromCalifornia : I ' m not against self - expression , but when I see high school students getting these piercing , I really wonder . In some cases , the drive is deeper and darker than mere fashion . A friend of mine tried piercing her own tongue with a safety pin . It got infected and she had a tongue the size of a cow ' s . Jackson fromOhio : I do n ' t think it ' s wrong , but when people do it all over the place like their face and everything - - I think that ' s ridiculous . People who get the big dragons that cover your whole body - - I do n ' t think that ' s necessary . When I see naked chicks on guys , I think . \" You have no respect for women . \" Brittney from New York :", "questions": "The best title for this passage is probably", "options": {"model": ["the import of death in the west", "body art or causing damage"], "human": ["Doing Damage to the Young People ' s Bodies", "Body Art or Causing Damage"]}, "answer": {"model": 1, "human": 1}}